{
	"easycom": {
		"autoscan": true,
		"custom": {
			"^u-(.*)": "@/uni_modules/uview-ui/components/u-$1/u-$1.vue"
		}
	},
	"pages": [
		{
			"path": "pages/index/index",
			"style": {
				"navigationBarTitleText": "登录"
			}
		},
		{
			"path": "pages/home",
			"style": {
				"navigationBarTitleText": "首页",
				"enablePullDownRefresh": false
			}
		},
		{
			"path": "pages/service",
			"style": {
				"navigationBarTitleText": "服务",
				"enablePullDownRefresh": false
			}
		},
		{
			"path": "pages/shuju",
			"style": {
				"navigationBarTitleText": "数据"
			}
		},
		{
			"path": "pages/myPage",
			"style": {
				"navigationBarTitleText": "我的"
			}
		},
		{
			"path": "pages/myPage/settings",
			"style": {
				"navigationBarTitleText": "账号与安全"
			}
		},
		{
			"path": "pages/Ai",
			"style": {
				"navigationBarTitleText": "Ai"
			}
		},
		{
			"path": "pages/myPage/about",
			"style": {
				"navigationBarTitleText": "关于我们"
			}
		},
		{
			"path": "pages/myPage/userInfo/email",
			"style": {
				"navigationBarTitleText": "邮箱"
			}
		},
		{
			"path" : "pages/myPage/userInfo/ChangePassword",
			"style" : 
			{
				"navigationBarTitleText" : "修改密码"
			}
		},
		{
			"path" : "pages/myPage/userInfo/ResetPwd",
			"style" : 
			{
				"navigationBarTitleText" : "重置密码"
			}
		},
		{
			"path" : "pages/myPage/AboutInfo/functionPage",
			"style" : 
			{
				"navigationBarTitleText" : "功能介绍"
			}
		},
		{
			"path" : "pages/register",
			"style" : 
			{
				"navigationBarTitleText" : "注册"
			}
		},
		{
			"path" : "pages/myPage/privacy",
			"style" : 
			{
				"navigationBarTitleText" : "隐私政策"
			}
		},
		{
			"path" : "pages/myPage/userInfo/userInfo",
			"style" : 
			{
				"navigationBarTitleText" : "个人资料"
			}
		}
	],
	"tabBar": {
		"list": [
			{
				"pagePath": "pages/home",
				"text": "首页",
				"iconPath": "https://launcher-car-assets.vercel.app/static/首页.png",
                "selectedIconPath": "https://launcher-car-assets.vercel.app/static/首页s.png"
			},
			{
				"pagePath": "pages/service",
				"text": "服务",
				"iconPath": "https://launcher-car-assets.vercel.app/static/服务.png",
                "selectedIconPath": "https://launcher-car-assets.vercel.app/static/服务s.png"
			},
			{
				"pagePath": "pages/shuju",
				"text": "数据",
				"iconPath": "https://launcher-car-assets.vercel.app/static/数据.png",
                "selectedIconPath": "https://launcher-car-assets.vercel.app/static/数据s.png"
			},
			{
				"pagePath": "pages/myPage",
				"text": "我的",
				"iconPath": "https://launcher-car-assets.vercel.app/static/我的.png",
                "selectedIconPath": "https://launcher-car-assets.vercel.app/static/我的s.png"
			}
		]
	},
	"globalStyle": {
		"navigationBarTextStyle": "black",
		"navigationBarTitleText": "uni-app",
		"navigationBarBackgroundColor": "#F8F8F8",
		"backgroundColor": "#F8F8F8"
	},
	"uniIdRouter": {}
}